str8ts_solver/README.md
str8ts_solver/__init__.py
str8ts_solver/_active_cells_utils.py
str8ts_solver/_check_solution.py
str8ts_solver/_str8ts_utils.py
str8ts_solver/output_utils.py
str8ts_solver/solver.py
str8ts_solver-0.2.2.dist-info/licenses/LICENSE
str8ts_solver-0.2.2.dist-info/METADATA
str8ts_solver-0.2.2.dist-info/WHEEL
str8ts_solver-0.2.2.dist-info/top_level.txt
str8ts_solver-0.2.2.dist-info/RECORD
