Metadata-Version: 2.4
Name: str8ts_solver
Version: 0.2.2
Summary: str8ts solver using z3
Author: Piotr Idzik
Author-email: vil02_str8ts_solver@10g.pl
Project-URL: repository, https://github.com/vil02/str8ts_solver
Keywords: str8ts,str8ts solver,z3
Requires-Python: >=3.12
License-File: LICENSE
Requires-Dist: z3-solver==4.15.4.0
Dynamic: license-file
